iminizinc/__init__.py
iminizinc/mzn.py
iminizinc/static/minizinc.js
iminizinc-0.4.dist-info/METADATA
iminizinc-0.4.dist-info/RECORD
iminizinc-0.4.dist-info/WHEEL
iminizinc-0.4.dist-info/top_level.txt
