Metadata-Version: 2.1
Name: iminizinc
Version: 0.4
Summary: IPython extensions for the MiniZinc constraint modelling language
Home-page: UNKNOWN
Author: Guido Tack
Author-email: guido.tack@monash.edu
License: UNKNOWN
Project-URL: Source, https://github.com/MiniZinc/iminizinc/
Project-URL: Tracker, https://github.com/MiniZinc/iminizinc/issues
Keywords: minizinc ipython
Platform: UNKNOWN
Classifier: Development Status :: 4 - Beta
Classifier: Intended Audience :: Developers
Classifier: Intended Audience :: Education
Classifier: Intended Audience :: Science/Research
Classifier: Topic :: Scientific/Engineering :: Artificial Intelligence
Classifier: Topic :: Scientific/Engineering :: Mathematics
Classifier: License :: OSI Approved :: Mozilla Public License 2.0 (MPL 2.0)
Classifier: Operating System :: OS Independent
Classifier: Programming Language :: Python :: 2
Classifier: Programming Language :: Python :: 2.7
Classifier: Programming Language :: Python :: 3
Classifier: Programming Language :: Python :: 3.2
Classifier: Programming Language :: Python :: 3.3
Classifier: Programming Language :: Python :: 3.4
Requires-Dist: ipython
